odoo/addons/sale_block_no_stock/README.rst
odoo/addons/sale_block_no_stock/__init__.py
odoo/addons/sale_block_no_stock/__manifest__.py
odoo/addons/sale_block_no_stock/i18n/es.po
odoo/addons/sale_block_no_stock/i18n/it.po
odoo/addons/sale_block_no_stock/i18n/pt.po
odoo/addons/sale_block_no_stock/i18n/sale_block_no_stock.pot
odoo/addons/sale_block_no_stock/models/__init__.py
odoo/addons/sale_block_no_stock/models/res_company.py
odoo/addons/sale_block_no_stock/models/res_config_settings.py
odoo/addons/sale_block_no_stock/models/sale_order.py
odoo/addons/sale_block_no_stock/readme/CONFIGURE.md
odoo/addons/sale_block_no_stock/readme/CONTEXT.md
odoo/addons/sale_block_no_stock/readme/CONTRIBUTORS.md
odoo/addons/sale_block_no_stock/readme/CREDITS.md
odoo/addons/sale_block_no_stock/readme/DESCRIPTION.md
odoo/addons/sale_block_no_stock/readme/USAGE.md
odoo/addons/sale_block_no_stock/security/ir.model.access.csv
odoo/addons/sale_block_no_stock/static/description/icon.png
odoo/addons/sale_block_no_stock/static/description/index.html
odoo/addons/sale_block_no_stock/tests/__init__.py
odoo/addons/sale_block_no_stock/tests/test_sale_block_no_stock.py
odoo/addons/sale_block_no_stock/views/res_config_settings_views.xml
odoo/addons/sale_block_no_stock/wizard/__init__.py
odoo/addons/sale_block_no_stock/wizard/sale_order_block_wizard.py
odoo/addons/sale_block_no_stock/wizard/sale_order_block_wizard_views.xml
odoo_addon_sale_block_no_stock-18.0.1.0.0.3.dist-info/METADATA
odoo_addon_sale_block_no_stock-18.0.1.0.0.3.dist-info/WHEEL
odoo_addon_sale_block_no_stock-18.0.1.0.0.3.dist-info/top_level.txt
odoo_addon_sale_block_no_stock-18.0.1.0.0.3.dist-info/RECORD
